faterunner/__init__.py
faterunner/__main__.py
faterunner/__version__.py
faterunner/parsers.py
faterunner-0.2.0.dist-info/METADATA
faterunner-0.2.0.dist-info/WHEEL
faterunner-0.2.0.dist-info/entry_points.txt
faterunner-0.2.0.dist-info/licenses/LICENSE
faterunner-0.2.0.dist-info/RECORD
