Metadata-Version: 2.4
Name: faterunner
Version: 0.2.0
Summary: F.. A.. Task Execution Runner
Project-URL: Homepage, https://github.com/sakhezech/faterunner
License-Expression: MIT
License-File: LICENSE
Classifier: Development Status :: 3 - Alpha
Classifier: Intended Audience :: Developers
Classifier: License :: OSI Approved :: MIT License
Classifier: Programming Language :: Python :: 3 :: Only
Classifier: Programming Language :: Python :: 3.11
Classifier: Programming Language :: Python :: 3.12
Classifier: Programming Language :: Python :: 3.13
Classifier: Programming Language :: Python :: 3.14
Classifier: Topic :: Software Development :: Build Tools
Classifier: Topic :: Utilities
Classifier: Typing :: Typed
Requires-Python: >=3.11
Provides-Extra: dev
Requires-Dist: ruff; extra == 'dev'
